tabulous/__init__.py
tabulous/__main__.py
tabulous/_async_importer.py
tabulous/_colormap.py
tabulous/_dtype.py
tabulous/_fetch_and_install.py
tabulous/_io.py
tabulous/_ipython.py
tabulous/_map_model.py
tabulous/_pd_index.py
tabulous/_range.py
tabulous/_selection_model.py
tabulous/_selection_op.py
tabulous/_slice_op.py
tabulous/_sort_filter_proxy.py
tabulous/_text_formatter.py
tabulous/_utils.py
tabulous/color.py
tabulous/core.py
tabulous/exceptions.py
tabulous/post_init.py
tabulous/threading.py
tabulous/types.py
tabulous/_keymap/__init__.py
tabulous/_keymap/_callback.py
tabulous/_keymap/_keymap_objects.py
tabulous/_keymap/_keymapview.py
tabulous/_magicgui/__init__.py
tabulous/_magicgui/_color_edit.py
tabulous/_magicgui/_dialog.py
tabulous/_magicgui/_register.py
tabulous/_magicgui/_selection.py
tabulous/_magicgui/_table.py
tabulous/_magicgui/_timedelta.py
tabulous/_magicgui/_toggle_switch.py
tabulous/_psygnal/__init__.py
tabulous/_psygnal/_array.py
tabulous/_psygnal/_psygnal_compat.py
tabulous/_psygnal/_slots.py
tabulous/_psygnal/_special_objects.py
tabulous/_qt/__init__.py
tabulous/_qt/_action_registry.py
tabulous/_qt/_app.py
tabulous/_qt/_clickable_label.py
tabulous/_qt/_dockwidget.py
tabulous/_qt/_filetree.py
tabulous/_qt/_history.py
tabulous/_qt/_jump.py
tabulous/_qt/_multitips.py
tabulous/_qt/_progress.py
tabulous/_qt/_proxy_button.py
tabulous/_qt/_qt_const.py
tabulous/_qt/_svg.py
tabulous/_qt/_titlebar.py
tabulous/_qt/_traceback.py
tabulous/_qt/_tree_header.py
tabulous/_qt/_undo.py
tabulous/_qt/_console/__init__.py
tabulous/_qt/_console/_widget.py
tabulous/_qt/_icons/barplot.svg
tabulous/_qt/_icons/boxenplot.svg
tabulous/_qt/_icons/boxplot.svg
tabulous/_qt/_icons/column_filter.svg
tabulous/_qt/_icons/copy.svg
tabulous/_qt/_icons/copy_as_spreadsheet.svg
tabulous/_qt/_icons/copy_as_table.svg
tabulous/_qt/_icons/cut.svg
tabulous/_qt/_icons/eval.svg
tabulous/_qt/_icons/filter.svg
tabulous/_qt/_icons/find_item.svg
tabulous/_qt/_icons/groupby.svg
tabulous-0.5.8.dist-info/METADATA
tabulous-0.5.8.dist-info/WHEEL
tabulous-0.5.8.dist-info/entry_points.txt
tabulous-0.5.8.dist-info/licenses/LICENSE
tabulous-0.5.8.dist-info/RECORD
