Metadata-Version: 2.3
Name: tabulous
Version: 0.5.8
Summary: A table data viewer for Python
Project-URL: Download, https://github.com/hanjinliu/tabulous
Author-email: Hanjin Liu <liuhanjin-sc@g.ecc.u-tokyo.ac.jp>
License: BSD 3-Clause License
License-File: LICENSE
Requires-Python: >=3.9
Requires-Dist: appdirs>=1.4.4
Requires-Dist: collections-undo>=0.0.7
Requires-Dist: magicgui!=0.8.3,>=0.7.0
Requires-Dist: matplotlib>=3.1
Requires-Dist: pandas>=1.5.2
Requires-Dist: psygnal>=0.9.0
Requires-Dist: qt-command-palette>=0.0.6
Requires-Dist: qtconsole
Requires-Dist: qtpy>=1.10.0
Requires-Dist: requests
Requires-Dist: tabulate
Requires-Dist: toml
Provides-Extra: all
Requires-Dist: pyqt5>=5.12.3; extra == 'all'
Requires-Dist: scikit-learn>=1.1; extra == 'all'
Requires-Dist: scipy>=1.7; extra == 'all'
Requires-Dist: seaborn>=0.11; extra == 'all'
Provides-Extra: pyqt5
Requires-Dist: pyqt5>=5.12.3; extra == 'pyqt5'
Provides-Extra: pyqt6
Requires-Dist: pyqt6>=6.3.1; extra == 'pyqt6'
Provides-Extra: scikit-learn
Requires-Dist: scikit-learn>=1.0; extra == 'scikit-learn'
Provides-Extra: testing
Requires-Dist: pytest; extra == 'testing'
Requires-Dist: pytest-qt; extra == 'testing'
